langapi/__init__.py
langapi-0.0.3.dist-info/METADATA
langapi-0.0.3.dist-info/RECORD
langapi-0.0.3.dist-info/WHEEL
langapi-0.0.3.dist-info/top_level.txt
