Metadata-Version: 2.1
Name: langapi
Version: 0.0.3
Summary: Python module for Lang API - see https://docs.langapi.co/ for more information.
Home-page: https://github.com/peterlzhou/langapi-python
Author: Peter Zhou
Author-email: peter@langapi.co
License: MIT
Platform: UNKNOWN
Classifier: License :: OSI Approved :: MIT License
Classifier: Programming Language :: Python :: 3
Classifier: Programming Language :: Python :: 3.7
